LICENCE
README.md
setup.cfg
setup.py
factorioBlueprintAnalyser.egg-info/PKG-INFO
factorioBlueprintAnalyser.egg-info/SOURCES.txt
factorioBlueprintAnalyser.egg-info/dependency_links.txt
factorioBlueprintAnalyser.egg-info/requires.txt
factorioBlueprintAnalyser.egg-info/top_level.txt
factorio_blueprint_analyser/__init__.py
factorio_blueprint_analyser/blueprint.py
factorio_blueprint_analyser/blueprint_analyser.py
factorio_blueprint_analyser/config.py
factorio_blueprint_analyser/entity.py
factorio_blueprint_analyser/factorio.py
factorio_blueprint_analyser/item.py
factorio_blueprint_analyser/network.py
factorio_blueprint_analyser/node.py
factorio_blueprint_analyser/options.py
factorio_blueprint_analyser/recipe.py
factorio_blueprint_analyser/utils.py
factorio_blueprint_analyser/assets/factorio_raw/factorio_raw_min.json
tests/test_all_blueprints.py