Metadata-Version: 2.4
Name: factorioBlueprintAnalyser
Version: 1.3.6
Summary: A python library analyse Factorio Blueprints and find bottlenecks.
Home-page: https://github.com/tomansion/factorio_blueprint_analyser_app/
Author: Tom Mansion
License: MIT License
License-File: LICENCE
Requires-Dist: termcolor==2.0.1
Requires-Dist: PyYAML==6.0.2
Requires-Dist: pyvis==0.3.0
Dynamic: author
Dynamic: home-page
Dynamic: license
Dynamic: license-file
Dynamic: requires-dist
Dynamic: summary
